---
arturl_encode: "68747470733a2f2f62:6c6f672e6373646e2e6e65742f71715f33383431313739362f:61727469636c652f64657461696c732f313430363031343033"
layout: post
title: "深入理解Java源码编译机制从源代码到字节码的全过程"
date: 2025-01-14 23:44:46 +0800
description: "Java源码编译机制是指将Java源文件（.java文件）编译成字节码文件（.class文件）的过程"
keywords: "看java的代理源代码原理要先学会字节码"
categories: ['进阶教程', 'Java']
tags: ['类加载', '源码编译机制', '源文件', '字节码', 'Java']
artid: "140601403"
image:
    path: https://api.vvhan.com/api/bing?rand=sj&artid=140601403
    alt: "深入理解Java源码编译机制从源代码到字节码的全过程"
render_with_liquid: false
featuredImage: https://bing.ee123.net/img/rand?artid=140601403
featuredImagePreview: https://bing.ee123.net/img/rand?artid=140601403
---

# 深入理解Java源码编译机制：从源代码到字节码的全过程

#### 深入理解Java源码编译机制：从源代码到字节码的全过程

##### 简介

Java源码编译机制是指将Java源文件（.java文件）编译成字节码文件（.class文件）的过程。编译后的字节码文件可以在任何支持Java虚拟机（JVM）的设备上运行。本文详细介绍Java的编译过程，并通过代码示例和注释帮助理解每个步骤。

##### 编译过程概述

1. **源码编写**
2. **词法分析**
3. **语法分析**
4. **语义分析**
5. **字节码生成**
6. **类加载和执行**

##### 源码编写

编写Java源码文件，文件扩展名为
`.java`
。

```java
/**
 * HelloWorld 类
 * 包含一个 main 方法，输出 "Hello, World!"
 */
public class HelloWorld {
    public static void main(String[] args) {
        System.out.println("Hello, World!"); // 打印 "Hello, World!"
    }
}

```

##### 词法分析（Lexical Analysis）

编译器将源码拆分成单词（tokens），识别关键字、标识符、常量和符号等。

```java
public class HelloWorld {
    // 词法分析将源码拆分为多个 tokens:
    // [public, class, HelloWorld, {, public, static, void, main, (, String, [, ], args, ), {, System, ., out, ., println, (, "Hello, World!", ), ;, }, }]
}

```

##### 语法分析（Syntax Analysis）

编译器检查源码是否符合Java的语法规则，并生成抽象语法树（AST, Abstract Syntax Tree）。

```plaintext
HelloWorld
├── Class: HelloWorld
│   ├── Method: main
│   │   ├── Parameters: [String[] args]
│   │   └── Body: System.out.println("Hello, World!")

```

##### 语义分析（Semantic Analysis）

编译器进行类型检查，确保变量和方法的使用符合Java的语义规则。

```java
/**
 * 语义分析确保类型和变量使用正确
 * 确认 System.out.println("Hello, World!") 的调用是有效的
 */
public class HelloWorld {
    public static void main(String[] args) {
        System.out.println("Hello, World!"); // 打印 "Hello, World!"
    }
}

```

##### 字节码生成（Bytecode Generation）

编译器将AST转换为字节码，并生成
`.class`
文件。

```plaintext
// HelloWorld.class
public class HelloWorld {
    public static void main(java.lang.String[]);
      Code:
         0: getstatic     #2                  // Field java/lang/System.out:Ljava/io/PrintStream;
         3: ldc           #3                  // String Hello, World!
         5: invokevirtual #4                  // Method java/io/PrintStream.println:(Ljava/lang/String;)V
         8: return
}

```

##### 类加载和执行

JVM加载
`.class`
文件，并执行其中的字节码。

##### 编译器工作机制

Java编译器的主要任务是将源码转换为字节码。以下是一个简单的Java编译器实现流程：

```java
import javax.tools.JavaCompiler;
import javax.tools.ToolProvider;
import java.io.IOException;

/**
 * SimpleCompiler 类
 * 使用 JavaCompiler API 编译 HelloWorld.java
 */
public class SimpleCompiler {
    public static void main(String[] args) {
        // 获取系统Java编译器
        JavaCompiler compiler = ToolProvider.getSystemJavaCompiler();
        // 编译HelloWorld.java
        int result = compiler.run(null, null, null, "HelloWorld.java");
        // 检查编译结果
        if (result == 0) {
            System.out.println("编译成功");
        } else {
            System.out.println("编译失败");
        }
    }
}

```

##### 深入理解字节码

Java字节码是一种低级的、与平台无关的指令集，可以由JVM解释执行或进一步编译为特定平台的机器码。

以下是一个简单的字节码分析示例：

```java
/**
 * BytecodeExample 类
 * 包含一个 add 方法，返回两个整数的和
 */
public class BytecodeExample {
    public int add(int a, int b) {
        return a + b;
    }
}

```

编译后生成的字节码（使用
`javap -c BytecodeExample`
查看）：

```plaintext
Compiled from "BytecodeExample.java"
public class BytecodeExample {
  public BytecodeExample();
    Code:
       0: aload_0
       1: invokespecial #1                  // Method java/lang/Object."<init>":()V
       4: return

  public int add(int, int);
    Code:
       0: iload_1
       1: iload_2
       2: iadd
       3: ireturn
}

```

字节码说明：

* `aload_0`
  : 将局部变量表中索引为0的引用类型变量加载到操作数栈。
* `invokespecial`
  : 调用实例初始化方法
  `<init>`
  。
* `iload_1`
  ,
  `iload_2`
  : 将局部变量表中索引为1和2的int类型变量加载到操作数栈。
* `iadd`
  : 从操作数栈弹出两个int值，相加后将结果压回操作数栈。
* `ireturn`
  : 从方法返回int值。

##### 编译时注解处理

编译时注解处理是Java编译过程中的一个重要环节，允许开发者在编译期间生成代码、文件或执行其他任务。

以下是一个简单的编译时注解处理器示例：

1. **定义注解**
   :

   ```java
   import java.lang.annotation.ElementType;
   import java.lang.annotation.Retention;
   import java.lang.annotation.RetentionPolicy;
   import java.lang.annotation.Target;

   /**
    * @GenerateClass 注解
    * 用于生成类文件
    */
   @Retention(RetentionPolicy.SOURCE)
   @Target(ElementType.TYPE)
   public @interface GenerateClass {
       String value();
   }

   ```
2. **实现注解处理器**
   :

   ```java
   import javax.annotation.processing.AbstractProcessor;
   import javax.annotation.processing.Processor;
   import javax.annotation.processing.RoundEnvironment;
   import javax.annotation.processing.SupportedAnnotationTypes;
   import javax.annotation.processing.SupportedSourceVersion;
   import javax.lang.model.SourceVersion;
   import javax.lang.model.element.Element;
   import javax.lang.model.element.TypeElement;
   import javax.tools.JavaFileObject;
   import java.io.IOException;
   import java.io.Writer;
   import java.util.Set;

   /**
    * GenerateClassProcessor 注解处理器
    * 根据 @GenerateClass 注解生成类文件
    */
   @SupportedAnnotationTypes("GenerateClass")
   @SupportedSourceVersion(SourceVersion.RELEASE_8)
   public class GenerateClassProcessor extends AbstractProcessor {
       @Override
       public boolean process(Set<? extends TypeElement> annotations, RoundEnvironment roundEnv) {
           for (Element element : roundEnv.getElementsAnnotatedWith(GenerateClass.class)) {
               GenerateClass generateClass = element.getAnnotation(GenerateClass.class);
               String className = generateClass.value();
               try {
                   JavaFileObject file = processingEnv.getFiler().createSourceFile(className);
                   try (Writer writer = file.openWriter()) {
                       writer.write("public class " + className + " {\n");
                       writer.write("    public void hello() {\n");
                       writer.write("        System.out.println(\"Hello from \" + " + className + ".class.getSimpleName());\n");
                       writer.write("    }\n");
                       writer.write("}\n");
                   }
               } catch (IOException e) {
                   e.printStackTrace();
               }
           }
           return true;
       }
   }

   ```
3. **使用注解**
   :

   ```java
   /**
    * 使用 @GenerateClass 注解
    * 将生成名为 GeneratedHello 的类
    */
   @GenerateClass("GeneratedHello")
   public class HelloWorld {
       public static void main(String[] args) {
           new GeneratedHello().hello(); // 调用生成的类的方法
       }
   }

   ```

   编译后将生成一个名为
   `GeneratedHello`
   的类，并在
   `HelloWorld`
   中调用它。

##### 总结

Java源码编译机制是一个复杂而精密的过程，涉及词法分析、语法分析、语义分析、字节码生成和优化。编译器不仅将源码转换为字节码，还会在编译过程中进行类型检查和优化，以提高代码的安全性和执行效率。理解编译机制有助于编写高效、健壮的Java程序，并在需要时编写自定义注解处理器以扩展编译器的功能。